[
  {
    "rank": 1,
    "name": "G4tts Twitch"
  },
  {
    "rank": 2,
    "name": "uI"
  },
  {
    "rank": 3,
    "name": "AlienManaBanana",
    "country": "us"
  },
  {
    "rank": 4,
    "name": "Porty",
    "team_id": 10053545,
    "team_tag": "EARTH",
    "country": "pe"
  },
  {
    "rank": 5,
    "name": "不着生死·一劍留禪",
    "team_id": 8502084,
    "team_tag": "",
    "country": "cn"
  },
  {
    "rank": 6,
    "name": "Lifo"
  },
  {
    "rank": 7,
    "name": "Queit"
  },
  {
    "rank": 8,
    "name": "KAz´"
  },
  {
    "rank": 9,
    "name": "DNG.MIR"
  },
  {
    "rank": 10,
    "name": "Life"
  },
  {
    "rank": 11,
    "name": "kpr2",
    "team_id": 9705410,
    "team_tag": "GP",
    "country": "pe"
  },
  {
    "rank": 12,
    "name": "MidNight",
    "country": "pe"
  },
  {
    "rank": 13,
    "name": "  ",
    "country": "pe"
  },
  {
    "rank": 14,
    "name": "Rich"
  },
  {
    "rank": 15,
    "name": "HaixeL",
    "country": "as"
  },
  {
    "rank": 16,
    "name": "Stars"
  },
  {
    "rank": 17,
    "name": "Anne",
    "team_id": 9062362,
    "team_tag": "N|era"
  },
  {
    "rank": 18,
    "name": "KIRIOS.BE",
    "country": "pe"
  },
  {
    "rank": 19,
    "name": "时间也自成冬"
  },
  {
    "rank": 19,
    "name": "hehe",
    "country": "ph"
  },
  {
    "rank": 21,
    "name": "PAPA`SMURF"
  },
  {
    "rank": 22,
    "name": "Akia",
    "country": "br"
  },
  {
    "rank": 23,
    "name": "Seven"
  },
  {
    "rank": 24,
    "name": "datebaio"
  },
  {
    "rank": 25,
    "name": "woods enjoyer"
  },
  {
    "rank": 26,
    "name": "bloodsmokinglory",
    "team_id": 9505143,
    "team_tag": "",
    "country": "us"
  },
  {
    "rank": 27,
    "name": "Valakas"
  },
  {
    "rank": 28,
    "name": "Xariton"
  },
  {
    "rank": 29,
    "name": "wakemeup",
    "team_id": 7584152,
    "team_tag": "TB"
  },
  {
    "rank": 30,
    "name": "Manchego",
    "team_id": 9928800,
    "team_tag": "DDS",
    "country": "bo"
  },
  {
    "rank": 31,
    "name": "Big Boy",
    "team_id": 10053545,
    "team_tag": "EARTH",
    "country": "pe"
  },
  {
    "rank": 32,
    "name": "Sheggy"
  },
  {
    "rank": 33,
    "name": "Got`Cha",
    "country": "pe"
  },
  {
    "rank": 34,
    "name": "Maru~"
  },
  {
    "rank": 35,
    "name": "lowskil",
    "team_id": 9256505,
    "team_tag": "pudj"
  },
  {
    "rank": 36,
    "name": "代表党中央和国务院"
  },
  {
    "rank": 37,
    "name": "Eeeip"
  },
  {
    "rank": 38,
    "name": ".",
    "country": "ph"
  },
  {
    "rank": 39,
    "name": "JosdKing"
  },
  {
    "rank": 40,
    "name": "Enigma",
    "country": "ca"
  },
  {
    "rank": 41,
    "name": "Rata Grandasa fedeadora de Uglys"
  },
  {
    "rank": 42,
    "name": "monadic",
    "team_id": 8877860,
    "team_tag": "",
    "country": "mn"
  },
  {
    "rank": 43,
    "name": "Pan Doge",
    "team_id": 5161685,
    "team_tag": "",
    "country": "ai"
  },
  {
    "rank": 44,
    "name": "afsjk"
  },
  {
    "rank": 45,
    "name": "Bobby Fischer Incarnate"
  },
  {
    "rank": 46,
    "name": "Greed"
  },
  {
    "rank": 47,
    "name": "Daisu"
  },
  {
    "rank": 48,
    "name": "SebasTrix"
  },
  {
    "rank": 49,
    "name": "RUSOTUVIEJAPRRA"
  },
  {
    "rank": 50,
    "name": "Splinter",
    "country": "pe"
  },
  {
    "rank": 51,
    "name": "RedPanda"
  },
  {
    "rank": 52,
    "name": "ARQUIDOTERO"
  },
  {
    "rank": 53,
    "name": "Aragon"
  },
  {
    "rank": 54,
    "name": "Danna AS"
  },
  {
    "rank": 55,
    "name": "Nacho Varga",
    "country": "pe"
  },
  {
    "rank": 56,
    "name": "Sr.Pulgosexo♡01",
    "country": "cn"
  },
  {
    "rank": 57,
    "name": "***"
  },
  {
    "rank": 58,
    "name": "好好休息",
    "country": "cn"
  },
  {
    "rank": 59,
    "name": "☯꧁️☠️❦ゑRL@N☠☯",
    "team_id": 5107877,
    "team_tag": ""
  },
  {
    "rank": 60,
    "name": "xdxXDXxd",
    "team_id": 9724297,
    "team_tag": " "
  },
  {
    "rank": 61,
    "name": "N i l o"
  },
  {
    "rank": 62,
    "name": "Canadian_Serge"
  },
  {
    "rank": 63,
    "name": "Eze",
    "team_id": 9277524,
    "team_tag": "",
    "country": "pe"
  },
  {
    "rank": 64,
    "name": "Mercy--",
    "team_id": 8125488,
    "team_tag": "FK",
    "country": "pe"
  },
  {
    "rank": 65,
    "name": "EERT"
  },
  {
    "rank": 65,
    "name": "Deaccon",
    "team_id": 4750836,
    "team_tag": ""
  },
  {
    "rank": 67,
    "name": "Tamalon"
  },
  {
    "rank": 68,
    "name": "Miralx-",
    "team_id": 9736744,
    "team_tag": "4Luv"
  },
  {
    "rank": 69,
    "name": "VoDka-KimimarO"
  },
  {
    "rank": 70,
    "name": "nhk",
    "team_id": 5038167,
    "team_tag": "",
    "country": "bo"
  },
  {
    "rank": 71,
    "name": "The Promise",
    "team_id": 9166860,
    "team_tag": "aefa",
    "country": "pe"
  },
  {
    "rank": 72,
    "name": "~~~",
    "country": "af"
  },
  {
    "rank": 73,
    "name": "Cali",
    "country": "pe"
  },
  {
    "rank": 74,
    "name": "xfoxx"
  },
  {
    "rank": 75,
    "name": "zayyar_Lrnz ",
    "country": "us"
  },
  {
    "rank": 75,
    "name": "chill-",
    "country": "af"
  },
  {
    "rank": 77,
    "name": "JACK DANIEL'S"
  },
  {
    "rank": 78,
    "name": "©@LÏ©Ø"
  },
  {
    "rank": 79,
    "name": "bloody"
  },
  {
    "rank": 80,
    "name": "Cabo^",
    "country": "pr"
  },
  {
    "rank": 81,
    "name": "Anakim"
  },
  {
    "rank": 82,
    "name": "11A"
  },
  {
    "rank": 83,
    "name": "Kardia 🦂"
  },
  {
    "rank": 84,
    "name": "Luchito"
  },
  {
    "rank": 85,
    "name": "Barsa",
    "country": "us"
  },
  {
    "rank": 86,
    "name": "Milfhunter",
    "team_id": 8361854,
    "team_tag": "Mboyz",
    "country": "us"
  },
  {
    "rank": 86,
    "name": "Kartier",
    "country": "cl"
  },
  {
    "rank": 88,
    "name": "Heisei10",
    "country": "pe"
  },
  {
    "rank": 89,
    "name": "ASDASDASD",
    "team_id": 8475690,
    "team_tag": "",
    "country": "pe"
  },
  {
    "rank": 90,
    "name": "ZacK.",
    "country": "pe"
  },
  {
    "rank": 91,
    "name": "Parfait",
    "country": "ph"
  },
  {
    "rank": 92,
    "name": "Lodka",
    "country": "pe"
  },
  {
    "rank": 93,
    "name": "Hisoka"
  },
  {
    "rank": 94,
    "name": "lytn"
  },
  {
    "rank": 95,
    "name": "Ramsa",
    "team_id": 9476603,
    "team_tag": "OlyG",
    "country": "pe"
  },
  {
    "rank": 96,
    "name": "Jed",
    "team_id": 7078190,
    "team_tag": "SL",
    "country": "pe"
  },
  {
    "rank": 97,
    "name": "SOuthSide",
    "country": "pe"
  },
  {
    "rank": 98,
    "name": "BoreALis",
    "team_id": 6241574,
    "team_tag": "COD"
  },
  {
    "rank": 99,
    "name": ".......",
    "team_id": 4841358,
    "team_tag": "SM",
    "country": "bo"
  },
  {
    "rank": 100,
    "name": "Im doing fine"
  },
  {
    "rank": 100,
    "name": "N[¤]Bu",
    "country": "bo"
  },
  {
    "rank": 102,
    "name": "Frintezza"
  },
  {
    "rank": 103,
    "name": "Jah",
    "team_id": 5072533,
    "team_tag": "",
    "country": "pe"
  },
  {
    "rank": 104,
    "name": "☺"
  },
  {
    "rank": 105,
    "name": "Filosoft",
    "country": "pe"
  },
  {
    "rank": 106,
    "name": "Dangerboy",
    "country": "pe"
  },
  {
    "rank": 107,
    "name": "GOBLIN"
  },
  {
    "rank": 108,
    "name": "Westeezy"
  },
  {
    "rank": 109,
    "name": "4113"
  },
  {
    "rank": 110,
    "name": "shylo"
  },
  {
    "rank": 111,
    "name": "蛋清",
    "country": "cn"
  },
  {
    "rank": 112,
    "name": "MaNia",
    "country": "pe"
  },
  {
    "rank": 112,
    "name": "Satori"
  },
  {
    "rank": 114,
    "name": "mistery",
    "country": "pe"
  },
  {
    "rank": 115,
    "name": "Lilith"
  },
  {
    "rank": 116,
    "name": "Pulpex-",
    "country": "pe"
  },
  {
    "rank": 117,
    "name": "NecrO"
  },
  {
    "rank": 118,
    "name": "price blyat",
    "team_id": 9717679,
    "team_tag": "",
    "country": "br"
  },
  {
    "rank": 119,
    "name": "Skull Leader",
    "country": "pl"
  },
  {
    "rank": 120,
    "name": "tv/hokagemd2",
    "team_id": 9760843,
    "team_tag": ""
  },
  {
    "rank": 121,
    "name": "George.GP",
    "team_id": 4213541,
    "team_tag": "TBG-"
  },
  {
    "rank": 122,
    "name": "Jnz-!",
    "country": "pe"
  },
  {
    "rank": 123,
    "name": "Unpredictable^_",
    "country": "pk"
  },
  {
    "rank": 124,
    "name": "Anonymous",
    "country": "br"
  },
  {
    "rank": 125,
    "name": "就是想贏啊"
  },
  {
    "rank": 126,
    "name": "Big Raga"
  },
  {
    "rank": 127,
    "name": "Hellokity"
  },
  {
    "rank": 128,
    "name": "Sdrawnl-",
    "team_id": 9018350,
    "team_tag": "777"
  },
  {
    "rank": 129,
    "name": "Ｋｕｒｏｋｙ",
    "team_id": 9346216,
    "team_tag": "WildCat",
    "country": "ni"
  },
  {
    "rank": 130,
    "name": "G Y U T A R O"
  },
  {
    "rank": 131,
    "name": "Kalash"
  },
  {
    "rank": 132,
    "name": "Rock Lee"
  },
  {
    "rank": 133,
    "name": "Rasec"
  },
  {
    "rank": 134,
    "name": "guccipradalouisvuitton",
    "team_id": 9828129,
    "team_tag": "LC",
    "country": "af"
  },
  {
    "rank": 135,
    "name": "VielSeer..:3",
    "country": "dz"
  },
  {
    "rank": 136,
    "name": "Dear My Boo"
  },
  {
    "rank": 137,
    "name": "Nyu :3"
  },
  {
    "rank": 138,
    "name": "P  A  I  N"
  },
  {
    "rank": 139,
    "name": "itamo"
  },
  {
    "rank": 140,
    "name": "Mr.Beans",
    "team_id": 7872701,
    "team_tag": "",
    "country": "pe"
  },
  {
    "rank": 141,
    "name": "saya"
  },
  {
    "rank": 142,
    "name": "y0nd"
  },
  {
    "rank": 143,
    "name": "15 AÑITOZ LIMPIANDO BAÑOS",
    "country": "af"
  },
  {
    "rank": 144,
    "name": "ted",
    "country": "pe"
  },
  {
    "rank": 145,
    "name": "⠀",
    "country": "af"
  },
  {
    "rank": 146,
    "name": "sanity is gone"
  },
  {
    "rank": 146,
    "name": "LaréTz",
    "country": "br"
  },
  {
    "rank": 148,
    "name": "Neil"
  },
  {
    "rank": 149,
    "name": "sunsy"
  },
  {
    "rank": 150,
    "name": " Puchito Enjoyer ",
    "country": "al"
  },
  {
    "rank": 151,
    "name": "S"
  },
  {
    "rank": 151,
    "name": "Waste"
  },
  {
    "rank": 153,
    "name": "DarkShadow",
    "country": "pe"
  },
  {
    "rank": 154,
    "name": "Xakyy~",
    "team_id": 8555384,
    "team_tag": "",
    "country": "mn"
  },
  {
    "rank": 155,
    "name": "Global Barred",
    "country": "af"
  },
  {
    "rank": 156,
    "name": "Shiro Fubuki",
    "team_id": 9366445,
    "team_tag": "",
    "country": "pe"
  },
  {
    "rank": 157,
    "name": "Darrelll!!"
  },
  {
    "rank": 157,
    "name": "Scum Funk",
    "team_id": 5016333,
    "team_tag": ""
  },
  {
    "rank": 159,
    "name": "SammyFanatic",
    "country": "us"
  },
  {
    "rank": 160,
    "name": "FerrazL",
    "team_id": 9572165,
    "team_tag": "Agressiv",
    "country": "br"
  },
  {
    "rank": 161,
    "name": "LostAngel",
    "team_id": 8696218,
    "team_tag": "Dino",
    "country": "pe"
  },
  {
    "rank": 162,
    "name": "x"
  },
  {
    "rank": 163,
    "name": "asd"
  },
  {
    "rank": 164,
    "name": "ArtStyle",
    "country": "ao"
  },
  {
    "rank": 165,
    "name": "Jessie",
    "country": "af"
  },
  {
    "rank": 166,
    "name": "NiceLag",
    "team_id": 9724293,
    "team_tag": "LNS",
    "country": "np"
  },
  {
    "rank": 166,
    "name": "I'm short guys :C"
  },
  {
    "rank": 168,
    "name": "Axmalot"
  },
  {
    "rank": 168,
    "name": "KerZel_Kz!"
  },
  {
    "rank": 168,
    "name": "sighted"
  },
  {
    "rank": 171,
    "name": "LRALRELRILROLRU.",
    "country": "pe"
  },
  {
    "rank": 171,
    "name": "HOPE",
    "country": "pe"
  },
  {
    "rank": 173,
    "name": "Artyk"
  },
  {
    "rank": 174,
    "name": "Suampo",
    "country": "pe"
  },
  {
    "rank": 175,
    "name": "secreTd0ta1",
    "team_id": 9577761,
    "team_tag": "PAREDÃO"
  },
  {
    "rank": 176,
    "name": "FishBoyM",
    "team_id": 2546670,
    "team_tag": "IB |",
    "country": "pe"
  },
  {
    "rank": 176,
    "name": "peru"
  },
  {
    "rank": 178,
    "name": "Yphexe"
  },
  {
    "rank": 178,
    "name": "Biaaasi",
    "country": "pe"
  },
  {
    "rank": 180,
    "name": "castanha"
  },
  {
    "rank": 181,
    "name": "GriMeS",
    "team_id": 2850423,
    "team_tag": "",
    "country": "bo"
  },
  {
    "rank": 182,
    "name": "D´Ali",
    "country": "dz"
  },
  {
    "rank": 182,
    "name": "woLF"
  },
  {
    "rank": 184,
    "name": "Badman",
    "country": "pe"
  },
  {
    "rank": 185,
    "name": "Joke"
  },
  {
    "rank": 186,
    "name": "989",
    "team_id": 2634068,
    "team_tag": "VEG",
    "country": "us"
  },
  {
    "rank": 187,
    "name": "Atencio",
    "team_id": 8988255,
    "team_tag": "CCT",
    "country": "pe"
  },
  {
    "rank": 188,
    "name": "LaMaravilla"
  },
  {
    "rank": 189,
    "name": "Alpha",
    "team_id": 9893944,
    "team_tag": "TS5",
    "country": "us"
  },
  {
    "rank": 190,
    "name": "Juuzou"
  },
  {
    "rank": 191,
    "name": "cain"
  },
  {
    "rank": 191,
    "name": "Mapache Killer",
    "country": "pe"
  },
  {
    "rank": 193,
    "name": "Zyrein"
  },
  {
    "rank": 194,
    "name": "murder",
    "country": "bs"
  },
  {
    "rank": 195,
    "name": "ttv/Virsatus",
    "country": "us"
  },
  {
    "rank": 196,
    "name": "Lob"
  },
  {
    "rank": 197,
    "name": "MORDEKAI"
  },
  {
    "rank": 198,
    "name": "Aniforce",
    "team_id": 9023875,
    "team_tag": "icon6"
  },
  {
    "rank": 199,
    "name": "iWin"
  },
  {
    "rank": 200,
    "name": "Journey",
    "team_id": 8084200,
    "team_tag": "NBLA",
    "country": "ee"
  },
  {
    "rank": 201,
    "name": "Daneszz''* pa ti hdptaa",
    "team_id": 8843849,
    "team_tag": "Vicious Y"
  },
  {
    "rank": 202,
    "name": "Aelo",
    "team_id": 2627781,
    "team_tag": "",
    "country": "pe"
  },
  {
    "rank": 203,
    "name": "Krest"
  },
  {
    "rank": 204,
    "name": "Krosty"
  },
  {
    "rank": 204,
    "name": "MEL",
    "country": "ax"
  },
  {
    "rank": 206,
    "name": "Heaven",
    "team_id": 9380949,
    "team_tag": "@",
    "country": "co"
  },
  {
    "rank": 207,
    "name": "..",
    "country": "cn"
  },
  {
    "rank": 208,
    "name": "Wally",
    "country": "pe"
  },
  {
    "rank": 209,
    "name": "♏︎ChuanStyler 🖤🖤",
    "country": "pe"
  },
  {
    "rank": 210,
    "name": "._."
  },
  {
    "rank": 211,
    "name": "Anoobtok",
    "team_id": 9691388,
    "team_tag": "",
    "country": "us"
  },
  {
    "rank": 212,
    "name": "Amanet"
  },
  {
    "rank": 213,
    "name": "月挽星回"
  },
  {
    "rank": 214,
    "name": "-.-",
    "team_id": 6658794,
    "team_tag": "",
    "country": "cn"
  },
  {
    "rank": 215,
    "name": "Misha_Ml"
  },
  {
    "rank": 215,
    "name": "Falcon",
    "country": "mn"
  },
  {
    "rank": 217,
    "name": "cOrajee",
    "country": "pe"
  },
  {
    "rank": 218,
    "name": "Mijae",
    "team_id": 7868621,
    "team_tag": "Maybe",
    "country": "pe"
  },
  {
    "rank": 219,
    "name": "HE VUELTO!",
    "country": "al"
  },
  {
    "rank": 220,
    "name": "Chicken Joe"
  },
  {
    "rank": 221,
    "name": "Radamez",
    "country": "ec"
  },
  {
    "rank": 222,
    "name": "†((K-oz))†",
    "team_id": 1578650,
    "team_tag": "SF.",
    "country": "bo"
  },
  {
    "rank": 223,
    "name": "Chino"
  },
  {
    "rank": 224,
    "name": "Hype"
  },
  {
    "rank": 225,
    "name": "☠☠☠hook☠☠☠"
  },
  {
    "rank": 226,
    "name": "Gotti A",
    "team_id": 9635531,
    "team_tag": "KURO",
    "country": "pe"
  },
  {
    "rank": 227,
    "name": "YOTOT",
    "team_id": 9678342,
    "team_tag": "KUPS",
    "country": "ph"
  },
  {
    "rank": 228,
    "name": "Dreyson"
  },
  {
    "rank": 229,
    "name": "Ron31",
    "team_id": 7312293,
    "team_tag": "NP",
    "country": "pe"
  },
  {
    "rank": 230,
    "name": "S4N_H0L0"
  },
  {
    "rank": 231,
    "name": "Skrell"
  },
  {
    "rank": 232,
    "name": "Niko"
  },
  {
    "rank": 233,
    "name": "lovelove"
  },
  {
    "rank": 234,
    "name": "."
  },
  {
    "rank": 235,
    "name": "Pizza",
    "team_id": 4189483,
    "team_tag": "DPG",
    "country": "ca"
  },
  {
    "rank": 236,
    "name": "† ShAdOw †",
    "team_id": 3328412,
    "team_tag": "NG",
    "country": "bo"
  },
  {
    "rank": 237,
    "name": "Chrisss",
    "country": "pe"
  },
  {
    "rank": 238,
    "name": "Thependex32",
    "country": "pe"
  },
  {
    "rank": 239,
    "name": "peluchex1"
  },
  {
    "rank": 240,
    "name": "Lekvi Lomisa"
  },
  {
    "rank": 241,
    "name": "Mid or Safe"
  },
  {
    "rank": 242,
    "name": "genekov"
  },
  {
    "rank": 243,
    "name": "Emto"
  },
  {
    "rank": 244,
    "name": "Brae",
    "country": "us"
  },
  {
    "rank": 245,
    "name": "Mapacho ",
    "team_id": 8539023,
    "team_tag": "PBOYs",
    "country": "pe"
  },
  {
    "rank": 246,
    "name": "OLNY POS 4"
  },
  {
    "rank": 246,
    "name": "シPeQueDotA@ッジ",
    "team_id": 9854764,
    "team_tag": "y.a",
    "country": "bo"
  },
  {
    "rank": 248,
    "name": "Webi Wabo",
    "team_id": 8106029,
    "team_tag": "LLDD",
    "country": "pe"
  },
  {
    "rank": 249,
    "name": "Bokuwa",
    "country": "pe"
  },
  {
    "rank": 250,
    "name": "SeKai-",
    "team_id": 9109753,
    "team_tag": "NTC",
    "country": "br"
  },
  {
    "rank": 251,
    "name": "FIGARA"
  },
  {
    "rank": 252,
    "name": "Porthos"
  },
  {
    "rank": 253,
    "name": "HaveANiceDay",
    "team_id": 3094696,
    "team_tag": "Up",
    "country": "us"
  },
  {
    "rank": 254,
    "name": "016.ANS",
    "country": "pe"
  },
  {
    "rank": 255,
    "name": "bloom",
    "team_id": 9766828,
    "team_tag": "HotBoy",
    "country": "ax"
  },
  {
    "rank": 256,
    "name": "Mermaid"
  },
  {
    "rank": 257,
    "name": "枪炮是不长眼的"
  },
  {
    "rank": 258,
    "name": "L.AS.AS.D.AS"
  },
  {
    "rank": 259,
    "name": "Charly"
  },
  {
    "rank": 259,
    "name": "KenaHi",
    "country": "ec"
  },
  {
    "rank": 259,
    "name": "Snlork",
    "team_id": 8407208,
    "team_tag": "Monke"
  },
  {
    "rank": 262,
    "name": "4ng",
    "country": "af"
  },
  {
    "rank": 263,
    "name": "GUSHNIZZZ",
    "country": "ca"
  },
  {
    "rank": 264,
    "name": "ShanKers",
    "team_id": 5017405,
    "team_tag": "NF",
    "country": "bo"
  },
  {
    "rank": 264,
    "name": "Keva",
    "country": "us"
  },
  {
    "rank": 266,
    "name": "~Barto~"
  },
  {
    "rank": 267,
    "name": "xXxDarKilleRxXx",
    "team_id": 2475361,
    "team_tag": "InThu…"
  },
  {
    "rank": 267,
    "name": "EL DESVENDADOR",
    "country": "pe"
  },
  {
    "rank": 269,
    "name": "Sokiro.月亮",
    "team_id": 9215724,
    "team_tag": "DSE",
    "country": "cn"
  },
  {
    "rank": 270,
    "name": "hy",
    "team_id": 3317775,
    "team_tag": "MysteryF",
    "country": "my"
  },
  {
    "rank": 271,
    "name": "Tresdin",
    "team_id": 6204539,
    "team_tag": "IF",
    "country": "us"
  },
  {
    "rank": 272,
    "name": "TYG",
    "team_id": 3238061,
    "team_tag": "OM"
  },
  {
    "rank": 273,
    "name": "Popeye"
  },
  {
    "rank": 273,
    "name": "flashka"
  },
  {
    "rank": 273,
    "name": "KoKo"
  },
  {
    "rank": 276,
    "name": "karmah"
  },
  {
    "rank": 277,
    "name": "LuissCook",
    "country": "ve"
  },
  {
    "rank": 278,
    "name": "killurick"
  },
  {
    "rank": 279,
    "name": "Greed"
  },
  {
    "rank": 280,
    "name": "Bubulldog"
  },
  {
    "rank": 280,
    "name": "KnivesChau",
    "team_id": 749364,
    "team_tag": "",
    "country": "us"
  },
  {
    "rank": 282,
    "name": "kubikdanon",
    "country": "ua"
  },
  {
    "rank": 283,
    "name": "DiegoTwice"
  },
  {
    "rank": 284,
    "name": "El Gran Saiyaman"
  },
  {
    "rank": 285,
    "name": "keshi",
    "team_id": 9517959,
    "team_tag": "",
    "country": "us"
  },
  {
    "rank": 286,
    "name": "Jokic"
  },
  {
    "rank": 287,
    "name": "BHB",
    "team_id": 5216380,
    "team_tag": "plz",
    "country": "au"
  },
  {
    "rank": 288,
    "name": "Prodigy Molly",
    "team_id": 9432340,
    "team_tag": "",
    "country": "pe"
  },
  {
    "rank": 289,
    "name": "Faffy"
  },
  {
    "rank": 290,
    "name": "ToM",
    "team_id": 9082137,
    "team_tag": "Marriot"
  },
  {
    "rank": 290,
    "name": "Mr. J-",
    "team_id": 7269009,
    "team_tag": "CrK",
    "country": "pe"
  },
  {
    "rank": 292,
    "name": "zombotany2003"
  },
  {
    "rank": 293,
    "name": "best off,mid and hc"
  },
  {
    "rank": 293,
    "name": "AndinoExotico"
  },
  {
    "rank": 295,
    "name": "snowball"
  },
  {
    "rank": 296,
    "name": "Y"
  },
  {
    "rank": 297,
    "name": "BsB REBORN"
  },
  {
    "rank": 298,
    "name": "Джунсеба"
  },
  {
    "rank": 299,
    "name": "Blaze",
    "team_id": 5067410,
    "team_tag": ""
  },
  {
    "rank": 299,
    "name": "MuSLeY"
  },
  {
    "rank": 301,
    "name": "La PARED.Mouracle",
    "team_id": 9577761,
    "team_tag": "PAREDÃO",
    "country": "br"
  },
  {
    "rank": 301,
    "name": "><"
  },
  {
    "rank": 303,
    "name": "Katima ><"
  },
  {
    "rank": 303,
    "name": "Balnerth"
  },
  {
    "rank": 305,
    "name": "CIGARRETE"
  },
  {
    "rank": 306,
    "name": "krato",
    "team_id": 9277203,
    "team_tag": "",
    "country": "ca"
  },
  {
    "rank": 307,
    "name": "OWO_PIPIPI"
  },
  {
    "rank": 308,
    "name": "syl"
  },
  {
    "rank": 309,
    "name": "WaddlingDuck",
    "country": "us"
  },
  {
    "rank": 310,
    "name": "Kengri",
    "team_id": 8864621,
    "team_tag": "MEW",
    "country": "bo"
  },
  {
    "rank": 311,
    "name": "israel",
    "country": "pe"
  },
  {
    "rank": 311,
    "name": "Mxwll"
  },
  {
    "rank": 311,
    "name": "Stolas"
  },
  {
    "rank": 311,
    "name": "D R G",
    "country": "pe"
  },
  {
    "rank": 315,
    "name": "Rocket"
  },
  {
    "rank": 316,
    "name": "Shinzei"
  },
  {
    "rank": 317,
    "name": "EMPERADOR"
  },
  {
    "rank": 317,
    "name": "vg.poyoyo",
    "team_id": 8556748,
    "team_tag": "",
    "country": "af"
  },
  {
    "rank": 317,
    "name": "^^",
    "team_id": 9765949,
    "team_tag": "",
    "country": "ca"
  },
  {
    "rank": 320,
    "name": "Churkanov"
  },
  {
    "rank": 321,
    "name": "족관RiKiF@x♥"
  },
  {
    "rank": 322,
    "name": "Ippo Makunouchi"
  },
  {
    "rank": 322,
    "name": "Lambogatti"
  },
  {
    "rank": 324,
    "name": "botw",
    "country": "us"
  },
  {
    "rank": 325,
    "name": "EL.Cubano",
    "team_id": 8494711,
    "team_tag": ""
  },
  {
    "rank": 325,
    "name": "arteezysbastark",
    "team_id": 9607876,
    "team_tag": "TCat"
  },
  {
    "rank": 327,
    "name": "sabor"
  },
  {
    "rank": 328,
    "name": "UCSM. CALVIN (EL MITO)"
  },
  {
    "rank": 329,
    "name": "Puulnz"
  },
  {
    "rank": 330,
    "name": "anal walker"
  },
  {
    "rank": 331,
    "name": "恩佐î",
    "team_id": 3514410,
    "team_tag": ""
  },
  {
    "rank": 331,
    "name": "REDBRIDGECOOODN",
    "country": "wf"
  },
  {
    "rank": 333,
    "name": "Purple",
    "country": "pe"
  },
  {
    "rank": 334,
    "name": "Farmvilleguy"
  },
  {
    "rank": 335,
    "name": "asaomodedonttalktome"
  },
  {
    "rank": 336,
    "name": "strike :)"
  },
  {
    "rank": 337,
    "name": "Alice"
  },
  {
    "rank": 337,
    "name": "McGonogol"
  },
  {
    "rank": 339,
    "name": "umemiya"
  },
  {
    "rank": 340,
    "name": "Pierlly ♡︎♡︎♡"
  },
  {
    "rank": 341,
    "name": "Heroine | 295"
  },
  {
    "rank": 342,
    "name": "PIOx1.Chappie",
    "country": "cl"
  },
  {
    "rank": 343,
    "name": "cOraje^^!",
    "team_id": 4367922,
    "team_tag": "SG",
    "country": "pe"
  },
  {
    "rank": 344,
    "name": "rongote"
  },
  {
    "rank": 345,
    "name": "Deci"
  },
  {
    "rank": 345,
    "name": "Dzmo"
  },
  {
    "rank": 347,
    "name": "Not Nilc"
  },
  {
    "rank": 347,
    "name": "Trippple",
    "team_id": 8550684,
    "team_tag": "CNB",
    "country": "us"
  },
  {
    "rank": 349,
    "name": "gewinner"
  },
  {
    "rank": 350,
    "name": "XDDDDDD"
  },
  {
    "rank": 351,
    "name": "Mazukalele",
    "team_id": 456328,
    "team_tag": "Uulen Us",
    "country": "mn"
  },
  {
    "rank": 352,
    "name": "TasteyBalls",
    "team_id": 5203602,
    "team_tag": "UMB",
    "country": "us"
  },
  {
    "rank": 352,
    "name": "Perritadead"
  },
  {
    "rank": 354,
    "name": "                               1",
    "country": "ax"
  },
  {
    "rank": 355,
    "name": "V i r u s"
  },
  {
    "rank": 356,
    "name": "Kirag-",
    "country": "us"
  },
  {
    "rank": 357,
    "name": "°CHABA°"
  },
  {
    "rank": 357,
    "name": "Promise"
  },
  {
    "rank": 359,
    "name": "caju",
    "team_id": 9080605,
    "team_tag": "TL",
    "country": "br"
  },
  {
    "rank": 360,
    "name": "Amber Herd"
  },
  {
    "rank": 360,
    "name": "Swagger Jagger"
  },
  {
    "rank": 360,
    "name": "Ilia Topuria"
  },
  {
    "rank": 363,
    "name": "Lotso",
    "country": "pe"
  },
  {
    "rank": 363,
    "name": "Nana"
  },
  {
    "rank": 365,
    "name": "Beatrice",
    "team_id": 5514742,
    "team_tag": "",
    "country": "dz"
  },
  {
    "rank": 366,
    "name": "Jorge",
    "country": "pe"
  },
  {
    "rank": 367,
    "name": "Heidi"
  },
  {
    "rank": 368,
    "name": "nowaifunolaifu",
    "country": "af"
  },
  {
    "rank": 369,
    "name": "AlcN",
    "country": "mx"
  },
  {
    "rank": 369,
    "name": "Devoiden"
  },
  {
    "rank": 371,
    "name": "Santhe",
    "team_id": 2678110,
    "team_tag": "/ONE"
  },
  {
    "rank": 372,
    "name": "Noah",
    "team_id": 9658105,
    "team_tag": "",
    "country": "us"
  },
  {
    "rank": 373,
    "name": "Piero"
  },
  {
    "rank": 374,
    "name": "Britney",
    "team_id": 9799590,
    "team_tag": "VRA"
  },
  {
    "rank": 375,
    "name": "Tefanito",
    "team_id": 8462987,
    "team_tag": "NFG"
  },
  {
    "rank": 375,
    "name": "*DMX*Жан-Поль Андре"
  },
  {
    "rank": 377,
    "name": "zzzzzzzɾ"
  },
  {
    "rank": 378,
    "name": "angelic richard",
    "country": "ar"
  },
  {
    "rank": 379,
    "name": "panda<",
    "team_id": 9956839,
    "team_tag": "LFT"
  },
  {
    "rank": 380,
    "name": "C4sin0",
    "team_id": 9438521,
    "team_tag": "Fat",
    "country": "pe"
  },
  {
    "rank": 381,
    "name": "先生"
  },
  {
    "rank": 382,
    "name": "Beck"
  },
  {
    "rank": 382,
    "name": "Urotsukidoji"
  },
  {
    "rank": 384,
    "name": "Saiko",
    "team_id": 7541758,
    "team_tag": ""
  },
  {
    "rank": 385,
    "name": "Lucerito",
    "team_id": 2418198,
    "team_tag": "T.A",
    "country": "pe"
  },
  {
    "rank": 385,
    "name": "Nicolette"
  },
  {
    "rank": 387,
    "name": "POWER"
  },
  {
    "rank": 388,
    "name": "egglog",
    "country": "ca"
  },
  {
    "rank": 389,
    "name": "Tysha <3 <",
    "country": "pe"
  },
  {
    "rank": 389,
    "name": "Ev4",
    "team_id": 7199293,
    "team_tag": "TheXg",
    "country": "pe"
  },
  {
    "rank": 391,
    "name": "B L A M E  -  K I L L Y"
  },
  {
    "rank": 392,
    "name": "Tachibana-",
    "team_id": 9538869,
    "team_tag": "TR.SSJ",
    "country": "pe"
  },
  {
    "rank": 393,
    "name": "Plupo",
    "country": "us"
  },
  {
    "rank": 394,
    "name": "Aldeano",
    "team_id": 2541239,
    "team_tag": "Vi'Ga",
    "country": "mx"
  },
  {
    "rank": 395,
    "name": "-aDder"
  },
  {
    "rank": 395,
    "name": "KidTrigger"
  },
  {
    "rank": 397,
    "name": "IM2B",
    "country": "vn"
  },
  {
    "rank": 398,
    "name": "Nacho"
  },
  {
    "rank": 399,
    "name": "Chipolita"
  },
  {
    "rank": 400,
    "name": "Cael",
    "team_id": 7833684,
    "team_tag": "DH",
    "country": "us"
  },
  {
    "rank": 401,
    "name": "jeffie"
  },
  {
    "rank": 401,
    "name": "."
  },
  {
    "rank": 403,
    "name": "RIAS"
  },
  {
    "rank": 404,
    "name": "NUNCA DARÁS POR VIVO A HEROIC"
  },
  {
    "rank": 404,
    "name": "MSR",
    "team_id": 9373482,
    "team_tag": "[T.A.]"
  },
  {
    "rank": 404,
    "name": "TYOKUN",
    "team_id": 4985947,
    "team_tag": "ЯR",
    "country": "bv"
  },
  {
    "rank": 407,
    "name": "Slick Willy"
  },
  {
    "rank": 408,
    "name": "MisteriΩ"
  },
  {
    "rank": 409,
    "name": "Neiram",
    "team_id": 8591542,
    "team_tag": "",
    "country": "pe"
  },
  {
    "rank": 410,
    "name": "g14",
    "team_id": 6232861,
    "team_tag": "Kat",
    "country": "us"
  },
  {
    "rank": 411,
    "name": "Try again"
  },
  {
    "rank": 412,
    "name": "LiL Córdova",
    "team_id": 5190107,
    "team_tag": "Rage Lords",
    "country": "pe"
  },
  {
    "rank": 413,
    "name": "Maverick",
    "team_id": 5466807,
    "team_tag": "Krkn",
    "country": "us"
  },
  {
    "rank": 414,
    "name": "Hope"
  },
  {
    "rank": 415,
    "name": "Franco",
    "team_id": 9705410,
    "team_tag": "GP",
    "country": "pe"
  },
  {
    "rank": 416,
    "name": ":)",
    "team_id": 9186938,
    "team_tag": "asa",
    "country": "au"
  },
  {
    "rank": 417,
    "name": "[EM] 1999-  '7_ ...... MLFS ...'"
  },
  {
    "rank": 418,
    "name": "Clevatess",
    "country": "pe"
  },
  {
    "rank": 419,
    "name": "Tired ",
    "team_id": 5155899,
    "team_tag": "DG"
  },
  {
    "rank": 420,
    "name": "Gustafary.<"
  },
  {
    "rank": 421,
    "name": "Jin_Kaiser",
    "team_id": 8532580,
    "team_tag": "",
    "country": "pe"
  },
  {
    "rank": 422,
    "name": "Quetzal",
    "country": "pe"
  },
  {
    "rank": 423,
    "name": "Señor Gato"
  },
  {
    "rank": 424,
    "name": "TelePo"
  },
  {
    "rank": 425,
    "name": "Kappo",
    "team_id": 7586726,
    "team_tag": "",
    "country": "ua"
  },
  {
    "rank": 426,
    "name": "Kagami",
    "team_id": 9522811,
    "team_tag": "",
    "country": "pe"
  },
  {
    "rank": 427,
    "name": "SleppyDogo"
  },
  {
    "rank": 427,
    "name": "Songbird"
  },
  {
    "rank": 429,
    "name": "Mana"
  },
  {
    "rank": 430,
    "name": "Mustang",
    "team_id": 9855818,
    "team_tag": "",
    "country": "ru"
  },
  {
    "rank": 431,
    "name": "I don`t care"
  },
  {
    "rank": 432,
    "name": "Smolk"
  },
  {
    "rank": 433,
    "name": "x"
  },
  {
    "rank": 433,
    "name": "<<[AЯ!SΞ™]>"
  },
  {
    "rank": 435,
    "name": "lobotomy"
  },
  {
    "rank": 436,
    "name": "COLIN",
    "team_id": 1006994,
    "team_tag": "TBD",
    "country": "cn"
  },
  {
    "rank": 437,
    "name": "xakira-"
  },
  {
    "rank": 437,
    "name": "Lotso"
  },
  {
    "rank": 439,
    "name": "El Alcaudón"
  },
  {
    "rank": 440,
    "name": "nvrmnd_",
    "team_id": 4284483,
    "team_tag": "",
    "country": "id"
  },
  {
    "rank": 440,
    "name": ".55"
  },
  {
    "rank": 442,
    "name": "Salty<",
    "team_id": 7935237,
    "team_tag": "PimP",
    "country": "ca"
  },
  {
    "rank": 443,
    "name": "tysec"
  },
  {
    "rank": 444,
    "name": "23",
    "team_id": 4958953,
    "team_tag": "DK",
    "country": "pe"
  },
  {
    "rank": 445,
    "name": "Love Gabriela :3"
  },
  {
    "rank": 446,
    "name": "Yurei"
  },
  {
    "rank": 447,
    "name": "Doma"
  },
  {
    "rank": 447,
    "name": "5X30"
  },
  {
    "rank": 449,
    "name": "Azami",
    "country": "jp"
  },
  {
    "rank": 450,
    "name": "gara"
  },
  {
    "rank": 451,
    "name": "Makanaky"
  },
  {
    "rank": 452,
    "name": "Radamanthys"
  },
  {
    "rank": 453,
    "name": "Molinomio"
  },
  {
    "rank": 453,
    "name": "幾田りら"
  },
  {
    "rank": 455,
    "name": "EEXPLOD",
    "team_id": 2788090,
    "team_tag": "Mire<3",
    "country": "pe"
  },
  {
    "rank": 456,
    "name": "phanta"
  },
  {
    "rank": 456,
    "name": "froc",
    "team_id": 9323299,
    "team_tag": "SNCA"
  },
  {
    "rank": 458,
    "name": "Azwraith",
    "country": "pe"
  },
  {
    "rank": 459,
    "name": "zieg"
  },
  {
    "rank": 460,
    "name": "Noah Muller"
  },
  {
    "rank": 460,
    "name": "BISCOCHITO",
    "country": "pe"
  },
  {
    "rank": 462,
    "name": "Jets`",
    "country": "ca"
  },
  {
    "rank": 463,
    "name": "La Churquita",
    "team_id": 7263812,
    "team_tag": "GC",
    "country": "bo"
  },
  {
    "rank": 464,
    "name": "r5h16ht41"
  },
  {
    "rank": 464,
    "name": "Akashi"
  },
  {
    "rank": 466,
    "name": "Viridian",
    "team_id": 8264085,
    "team_tag": "",
    "country": "us"
  },
  {
    "rank": 467,
    "name": "BinT宾特",
    "country": "pe"
  },
  {
    "rank": 468,
    "name": "Packs.",
    "team_id": 1385837,
    "team_tag": "",
    "country": "pe"
  },
  {
    "rank": 469,
    "name": "Somco",
    "country": "pe"
  },
  {
    "rank": 469,
    "name": "Wildsoul-"
  },
  {
    "rank": 471,
    "name": "Indomitus",
    "country": "pe"
  },
  {
    "rank": 472,
    "name": "Silent",
    "team_id": 3480142,
    "team_tag": "SDLG",
    "country": "pe"
  },
  {
    "rank": 472,
    "name": "Now way"
  },
  {
    "rank": 474,
    "name": "Blizzard",
    "team_id": 5064861,
    "team_tag": "UW"
  },
  {
    "rank": 474,
    "name": "YVL",
    "team_id": 8390985,
    "team_tag": "",
    "country": "ar"
  },
  {
    "rank": 474,
    "name": "Keys <",
    "country": "pe"
  },
  {
    "rank": 477,
    "name": "Sakyuvi ♠",
    "team_id": 9255449,
    "team_tag": "SvT",
    "country": "ve"
  },
  {
    "rank": 478,
    "name": "MENOR BAJOGRAMA",
    "team_id": 9938060,
    "team_tag": "OG",
    "country": "pe"
  },
  {
    "rank": 478,
    "name": "RaGnaRoK",
    "team_id": 8701087,
    "team_tag": "",
    "country": "cn"
  },
  {
    "rank": 480,
    "name": "Bibabola~"
  },
  {
    "rank": 481,
    "name": "b"
  },
  {
    "rank": 482,
    "name": "XODÓ",
    "country": "pe"
  },
  {
    "rank": 483,
    "name": "Bald Head",
    "team_id": 9850342,
    "team_tag": "NB"
  },
  {
    "rank": 484,
    "name": "23",
    "country": "us"
  },
  {
    "rank": 484,
    "name": "Gufi Guber"
  },
  {
    "rank": 486,
    "name": "Darkscythe",
    "team_id": 4646793,
    "team_tag": "",
    "country": "pe"
  },
  {
    "rank": 487,
    "name": "Solar",
    "team_id": 2634364,
    "team_tag": "EX",
    "country": "cn"
  },
  {
    "rank": 487,
    "name": "UZI"
  },
  {
    "rank": 489,
    "name": "atuq"
  },
  {
    "rank": 490,
    "name": "Cole科尔",
    "country": "tt"
  },
  {
    "rank": 490,
    "name": "DOGBERT"
  },
  {
    "rank": 492,
    "name": "G.Pride|.saikoO",
    "team_id": 9717898,
    "team_tag": "G.PRIDE"
  },
  {
    "rank": 493,
    "name": "izy~ <",
    "country": "pe"
  },
  {
    "rank": 494,
    "name": "FlameTurtle"
  },
  {
    "rank": 495,
    "name": "Joxj",
    "team_id": 7453533,
    "team_tag": "T.Galactus",
    "country": "pe"
  },
  {
    "rank": 496,
    "name": "TerrorTed"
  },
  {
    "rank": 497,
    "name": "_Fake!!"
  },
  {
    "rank": 498,
    "name": "Durachok",
    "team_id": 7485937,
    "team_tag": "EGFD",
    "country": "ru"
  },
  {
    "rank": 498,
    "name": "sarnimm"
  },
  {
    "rank": 500,
    "name": "Kabeza10"
  }
]
