[
  {
    "rank": 1,
    "name": "Satanic",
    "team_id": 9824702,
    "team_tag": "PARI"
  },
  {
    "rank": 2,
    "name": "Nightfall",
    "team_id": 9467224,
    "team_tag": "Aurora"
  },
  {
    "rank": 3,
    "name": "Pure",
    "team_id": 8291895,
    "team_tag": "Tundra"
  },
  {
    "rank": 4,
    "name": "Save-",
    "team_id": 8255888,
    "team_tag": "BetBoom",
    "country": "md"
  },
  {
    "rank": 5,
    "name": "Kiritych~",
    "team_id": 8255888,
    "team_tag": "BetBoom",
    "country": "ru"
  },
  {
    "rank": 6,
    "name": "Niku",
    "team_id": 36,
    "team_tag": "NAVI",
    "country": "af"
  },
  {
    "rank": 7,
    "name": "Wisper",
    "team_id": 9303484,
    "team_tag": "HEROIC",
    "country": "bo"
  },
  {
    "rank": 8,
    "name": "NothingToSay",
    "team_id": 8261500,
    "team_tag": "XG"
  },
  {
    "rank": 9,
    "name": "Jankos",
    "country": "pl"
  },
  {
    "rank": 10,
    "name": "gotthejuice",
    "team_id": 36,
    "team_tag": "NAVI",
    "country": "cd"
  },
  {
    "rank": 11,
    "name": "rue",
    "team_id": 7119388,
    "team_tag": "TSpirit",
    "country": "bb"
  },
  {
    "rank": 12,
    "name": "Saksa",
    "country": "mk"
  },
  {
    "rank": 13,
    "name": "AMMAR_THE_F",
    "team_id": 9247354,
    "team_tag": "FLCN"
  },
  {
    "rank": 14,
    "name": "aik",
    "country": "kz"
  },
  {
    "rank": 15,
    "name": "jikroy",
    "team_id": 9829573,
    "team_tag": "RKX",
    "country": "ps"
  },
  {
    "rank": 16,
    "name": "医者watson`",
    "team_id": 9823272,
    "team_tag": "TY",
    "country": "kz"
  },
  {
    "rank": 17,
    "name": "9Class",
    "team_id": 9824702,
    "team_tag": "PARI"
  },
  {
    "rank": 18,
    "name": "Noticed",
    "team_id": 9823272,
    "team_tag": "TY"
  },
  {
    "rank": 19,
    "name": "swedenstrong",
    "team_id": 9255039,
    "team_tag": "1w",
    "country": "ru"
  },
  {
    "rank": 20,
    "name": "DM",
    "team_id": 9824702,
    "team_tag": "PARI"
  },
  {
    "rank": 21,
    "name": "OmaR",
    "team_id": 7554697,
    "team_tag": "NGX",
    "country": "lb"
  },
  {
    "rank": 22,
    "name": "CHIRA_JUNIOR",
    "team_id": 9823272,
    "team_tag": "TY",
    "country": "io"
  },
  {
    "rank": 23,
    "name": "TaiLung",
    "team_id": 9303484,
    "team_tag": "HEROIC"
  },
  {
    "rank": 24,
    "name": "OneJey ",
    "country": "by"
  },
  {
    "rank": 25,
    "name": "skem",
    "team_id": 2586976,
    "team_tag": "OG",
    "country": "ph"
  },
  {
    "rank": 26,
    "name": "Yatoro",
    "team_id": 7119388,
    "team_tag": "TSpirit"
  },
  {
    "rank": 27,
    "name": "squad1x",
    "team_id": 9255039,
    "team_tag": "1w"
  },
  {
    "rank": 28,
    "name": "lorenof"
  },
  {
    "rank": 29,
    "name": "ChodΣX",
    "country": "io"
  },
  {
    "rank": 30,
    "name": "Ari",
    "team_id": 8291895,
    "team_tag": "Tundra"
  },
  {
    "rank": 31,
    "name": "SSS",
    "team_id": 9255039,
    "team_tag": "1w"
  },
  {
    "rank": 32,
    "name": "Malr1ne",
    "team_id": 9247354,
    "team_tag": "FLCN",
    "country": "bi"
  },
  {
    "rank": 33,
    "name": "Tobi",
    "country": "at"
  },
  {
    "rank": 34,
    "name": "Shad",
    "country": "nl"
  },
  {
    "rank": 35,
    "name": "Stojkov",
    "country": "mk"
  },
  {
    "rank": 36,
    "name": "daze",
    "country": "kz"
  },
  {
    "rank": 37,
    "name": "dolbayob",
    "country": "af"
  },
  {
    "rank": 38,
    "name": "BOOM",
    "country": "cz"
  },
  {
    "rank": 39,
    "name": "GH",
    "team_id": 7554697,
    "team_tag": "NGX",
    "country": "lb"
  },
  {
    "rank": 40,
    "name": "Saberlight",
    "country": "cz"
  },
  {
    "rank": 41,
    "name": "bzm",
    "team_id": 8291895,
    "team_tag": "Tundra",
    "country": "as"
  },
  {
    "rank": 42,
    "name": "423",
    "team_id": 10019843,
    "team_tag": "ICxI",
    "country": "bw"
  },
  {
    "rank": 43,
    "name": "emptiness死"
  },
  {
    "rank": 44,
    "name": "gpk~",
    "team_id": 8255888,
    "team_tag": "BetBoom",
    "country": "af"
  },
  {
    "rank": 45,
    "name": "Dukalis",
    "team_id": 9824702,
    "team_tag": "PARI",
    "country": "ru"
  },
  {
    "rank": 46,
    "name": "Mikey"
  },
  {
    "rank": 47,
    "name": "Hellscream",
    "country": "by"
  },
  {
    "rank": 48,
    "name": "Darklord,,`",
    "country": "af"
  },
  {
    "rank": 49,
    "name": "RESPECT",
    "country": "by"
  },
  {
    "rank": 50,
    "name": "Worick"
  },
  {
    "rank": 51,
    "name": "skiter",
    "team_id": 9247354,
    "team_tag": "FLCN",
    "country": "sk"
  },
  {
    "rank": 52,
    "name": "mellojul",
    "team_id": 9928636,
    "team_tag": "LYNX",
    "country": "ax"
  },
  {
    "rank": 53,
    "name": "Aidar"
  },
  {
    "rank": 54,
    "name": "Natsumi",
    "team_id": 2586976,
    "team_tag": "OG"
  },
  {
    "rank": 55,
    "name": "Fayde",
    "team_id": 9964962,
    "team_tag": "GL"
  },
  {
    "rank": 56,
    "name": "fy",
    "team_id": 8261500,
    "team_tag": "XG"
  },
  {
    "rank": 57,
    "name": "Batyuk",
    "team_id": 10027397,
    "team_tag": "LFT",
    "country": "ua"
  },
  {
    "rank": 58,
    "name": "Thiolicor",
    "country": "br"
  },
  {
    "rank": 59,
    "name": "No!ob™",
    "team_id": 7554697,
    "team_tag": "NGX",
    "country": "lb"
  },
  {
    "rank": 60,
    "name": "kaori",
    "team_id": 9467224,
    "team_tag": "Aurora",
    "country": "al"
  },
  {
    "rank": 61,
    "name": "Till The End",
    "team_id": 55,
    "team_tag": "PR",
    "country": "af"
  },
  {
    "rank": 62,
    "name": "RCY",
    "team_id": 9964962,
    "team_tag": "GL",
    "country": "us"
  },
  {
    "rank": 63,
    "name": "dream`",
    "country": "kg"
  },
  {
    "rank": 64,
    "name": "htiviy_vladik",
    "team_id": 9928636,
    "team_tag": "LYNX",
    "country": "ua"
  },
  {
    "rank": 65,
    "name": "No[o]ne-",
    "team_id": 9824702,
    "team_tag": "PARI",
    "country": "au"
  },
  {
    "rank": 66,
    "name": "Daxao",
    "team_id": 9895392,
    "team_tag": "VP",
    "country": "ru"
  },
  {
    "rank": 67,
    "name": "tOfu",
    "team_id": 2163,
    "team_tag": "Liquid",
    "country": "de"
  },
  {
    "rank": 68,
    "name": "INFERNAL"
  },
  {
    "rank": 69,
    "name": "TA2000",
    "country": "kz"
  },
  {
    "rank": 70,
    "name": "bb3px",
    "country": "ru"
  },
  {
    "rank": 71,
    "name": "Yuragi",
    "country": "ua"
  },
  {
    "rank": 72,
    "name": "Malik"
  },
  {
    "rank": 73,
    "name": "Serenada",
    "team_id": 9872558,
    "team_tag": "VPP",
    "country": "ru"
  },
  {
    "rank": 74,
    "name": "sanctity",
    "country": "mn"
  },
  {
    "rank": 75,
    "name": "ssnovv1",
    "team_id": 9498970,
    "team_tag": "AVULUS",
    "country": "af"
  },
  {
    "rank": 76,
    "name": "bottega",
    "country": "ru"
  },
  {
    "rank": 77,
    "name": "Corrupted"
  },
  {
    "rank": 78,
    "name": "Riddys",
    "team_id": 36,
    "team_tag": "NAVI"
  },
  {
    "rank": 79,
    "name": "Abed",
    "team_id": 9895392,
    "team_tag": "VP",
    "country": "af"
  },
  {
    "rank": 80,
    "name": "yamich",
    "country": "ru"
  },
  {
    "rank": 81,
    "name": "Nikko",
    "team_id": 2586976,
    "team_tag": "OG",
    "country": "ph"
  },
  {
    "rank": 82,
    "name": "Cloud",
    "country": "ru"
  },
  {
    "rank": 83,
    "name": "JANTER",
    "team_id": 9872558,
    "team_tag": "VPP"
  },
  {
    "rank": 84,
    "name": "dualrazee",
    "team_id": 9498970,
    "team_tag": "AVULUS",
    "country": "ua"
  },
  {
    "rank": 85,
    "name": "tired_dog",
    "country": "hu"
  },
  {
    "rank": 86,
    "name": "Davai",
    "country": "be"
  },
  {
    "rank": 87,
    "name": "7jesu",
    "team_id": 9928636,
    "team_tag": "LYNX",
    "country": "ad"
  },
  {
    "rank": 88,
    "name": "SoNNeikO",
    "country": "uz"
  },
  {
    "rank": 89,
    "name": "darkniA",
    "team_id": 1838315,
    "team_tag": "Secret",
    "country": "by"
  },
  {
    "rank": 90,
    "name": "Ethereal",
    "team_id": 9895247,
    "team_tag": "RE"
  },
  {
    "rank": 91,
    "name": "fortniteMan",
    "country": "ua"
  },
  {
    "rank": 92,
    "name": "Ekki",
    "country": "pl"
  },
  {
    "rank": 93,
    "name": "Fly",
    "team_id": 9895392,
    "team_tag": "VP",
    "country": "as"
  },
  {
    "rank": 93,
    "name": "shigetsu",
    "country": "ua"
  },
  {
    "rank": 95,
    "name": "NLineは",
    "team_id": 9724050,
    "team_tag": "",
    "country": "bh"
  },
  {
    "rank": 96,
    "name": "Bengan"
  },
  {
    "rank": 96,
    "name": "Rein",
    "team_id": 9255039,
    "team_tag": "1w"
  },
  {
    "rank": 98,
    "name": "asdekor_r",
    "team_id": 9498970,
    "team_tag": "AVULUS",
    "country": "ru"
  },
  {
    "rank": 99,
    "name": "LenS"
  },
  {
    "rank": 100,
    "name": "4x",
    "country": "fi"
  },
  {
    "rank": 101,
    "name": "Sneyking",
    "team_id": 9247354,
    "team_tag": "FLCN",
    "country": "us"
  },
  {
    "rank": 102,
    "name": "bashka"
  },
  {
    "rank": 103,
    "name": "Mirage`",
    "country": "kz"
  },
  {
    "rank": 104,
    "name": "MikSa`",
    "country": "rs"
  },
  {
    "rank": 105,
    "name": "Stoic",
    "team_id": 9850034,
    "team_tag": "LFT"
  },
  {
    "rank": 106,
    "name": "Supream^",
    "country": "cz"
  },
  {
    "rank": 107,
    "name": "Rain"
  },
  {
    "rank": 108,
    "name": "Lelis"
  },
  {
    "rank": 108,
    "name": "Immersion",
    "country": "ru"
  },
  {
    "rank": 110,
    "name": "MieRo",
    "team_id": 8255888,
    "team_tag": "BetBoom"
  },
  {
    "rank": 111,
    "name": "Mo13ei",
    "country": "de"
  },
  {
    "rank": 112,
    "name": "not_me"
  },
  {
    "rank": 113,
    "name": "Copy",
    "country": "de"
  },
  {
    "rank": 114,
    "name": "Se",
    "team_id": 10019843,
    "team_tag": "ICxI",
    "country": "mn"
  },
  {
    "rank": 115,
    "name": "salamat1",
    "country": "cn"
  },
  {
    "rank": 116,
    "name": "rincyq",
    "country": "ua"
  },
  {
    "rank": 117,
    "name": "laise",
    "team_id": 10019843,
    "team_tag": "ICxI"
  },
  {
    "rank": 118,
    "name": "fashion",
    "team_id": 9368642,
    "team_tag": "shef",
    "country": "ai"
  },
  {
    "rank": 119,
    "name": "VaniLLl",
    "team_id": 5014799,
    "team_tag": "Nemiga",
    "country": "ru"
  },
  {
    "rank": 119,
    "name": "спортик",
    "country": "by"
  },
  {
    "rank": 121,
    "name": "waveformn",
    "country": "ru"
  },
  {
    "rank": 122,
    "name": "4IVAN"
  },
  {
    "rank": 123,
    "name": "Xenon",
    "country": "ru"
  },
  {
    "rank": 124,
    "name": "panto",
    "team_id": 7119388,
    "team_tag": "TSpirit",
    "country": "at"
  },
  {
    "rank": 125,
    "name": "KaChal"
  },
  {
    "rank": 126,
    "name": "Koma`",
    "country": "ru"
  },
  {
    "rank": 127,
    "name": "Scofield",
    "country": "pe"
  },
  {
    "rank": 128,
    "name": "мистер мораль",
    "country": "ru"
  },
  {
    "rank": 129,
    "name": "xNova",
    "team_id": 8261500,
    "team_tag": "XG"
  },
  {
    "rank": 130,
    "name": "Munkushi~太阳",
    "team_id": 9255039,
    "team_tag": "1w",
    "country": "ax"
  },
  {
    "rank": 130,
    "name": "Ankou ♡",
    "team_id": 9895247,
    "team_tag": "RE",
    "country": "ee"
  },
  {
    "rank": 132,
    "name": "ani-san",
    "team_id": 9895247,
    "team_tag": "RE",
    "country": "kz"
  },
  {
    "rank": 133,
    "name": "kae",
    "country": "ru"
  },
  {
    "rank": 134,
    "name": "cutie"
  },
  {
    "rank": 135,
    "name": "KingJungles",
    "team_id": 9303484,
    "team_tag": "HEROIC",
    "country": "br"
  },
  {
    "rank": 135,
    "name": "Kidaro",
    "country": "au"
  },
  {
    "rank": 137,
    "name": "spermashtern"
  },
  {
    "rank": 138,
    "name": "x",
    "country": "pr"
  },
  {
    "rank": 139,
    "name": "SumaiL-",
    "team_id": 7554697,
    "team_tag": "NGX",
    "country": "pk"
  },
  {
    "rank": 140,
    "name": "pma",
    "team_id": 36,
    "team_tag": "NAVI",
    "country": "ua"
  },
  {
    "rank": 141,
    "name": "Jîng",
    "country": "ph"
  },
  {
    "rank": 142,
    "name": "bot",
    "team_id": 9895392,
    "team_tag": "VP",
    "country": "af"
  },
  {
    "rank": 142,
    "name": "MinD_ContRoL",
    "country": "bg"
  },
  {
    "rank": 144,
    "name": "glimpse"
  },
  {
    "rank": 145,
    "name": "shizanagidoto (король)"
  },
  {
    "rank": 146,
    "name": "coldofff"
  },
  {
    "rank": 146,
    "name": "Malin",
    "country": "by"
  },
  {
    "rank": 148,
    "name": "звёзд怪物",
    "country": "bv"
  },
  {
    "rank": 148,
    "name": "Ame",
    "team_id": 8261500,
    "team_tag": "XG"
  },
  {
    "rank": 150,
    "name": "ponlo",
    "country": "sg"
  },
  {
    "rank": 151,
    "name": "niche",
    "country": "ua"
  },
  {
    "rank": 152,
    "name": "Nyx",
    "country": "az"
  },
  {
    "rank": 152,
    "name": "gringe",
    "country": "mn"
  },
  {
    "rank": 154,
    "name": "Norma"
  },
  {
    "rank": 155,
    "name": "TORONTOTOKYO",
    "country": "ru"
  },
  {
    "rank": 156,
    "name": "MoOz"
  },
  {
    "rank": 157,
    "name": "chempik",
    "country": "az"
  },
  {
    "rank": 158,
    "name": "MidOne",
    "country": "my"
  },
  {
    "rank": 159,
    "name": "tv/saillyn",
    "country": "ru"
  },
  {
    "rank": 160,
    "name": "Smiling Knight",
    "country": "by"
  },
  {
    "rank": 161,
    "name": "TIMS",
    "team_id": 2586976,
    "team_tag": "OG",
    "country": "ao"
  },
  {
    "rank": 162,
    "name": "Fernans",
    "country": "ua"
  },
  {
    "rank": 163,
    "name": "Amano",
    "team_id": 9766820,
    "team_tag": "ki",
    "country": "ru"
  },
  {
    "rank": 164,
    "name": "zarich"
  },
  {
    "rank": 165,
    "name": "Veldt"
  },
  {
    "rank": 166,
    "name": "Crystallis",
    "country": "nl"
  },
  {
    "rank": 167,
    "name": "zipzap",
    "country": "mk"
  },
  {
    "rank": 168,
    "name": "sayuw",
    "country": "ru"
  },
  {
    "rank": 169,
    "name": "queezy",
    "country": "al"
  },
  {
    "rank": 169,
    "name": "payk",
    "team_id": 9928403,
    "team_tag": "Cobra",
    "country": "pe"
  },
  {
    "rank": 171,
    "name": "mmxcnssaa",
    "country": "by"
  },
  {
    "rank": 172,
    "name": "Speeed",
    "team_id": 9964962,
    "team_tag": "GL",
    "country": "us"
  },
  {
    "rank": 173,
    "name": "hunghung"
  },
  {
    "rank": 174,
    "name": "whyalwaysme"
  },
  {
    "rank": 175,
    "name": "v1olent–",
    "country": "dz"
  },
  {
    "rank": 175,
    "name": "conjure.x",
    "country": "kz"
  },
  {
    "rank": 177,
    "name": "Qojqva",
    "country": "de"
  },
  {
    "rank": 178,
    "name": "Lqc."
  },
  {
    "rank": 179,
    "name": "MiLAN",
    "team_id": 9995792,
    "team_tag": "lft",
    "country": "ba"
  },
  {
    "rank": 180,
    "name": "4nalog丶01",
    "country": "it"
  },
  {
    "rank": 181,
    "name": "G.T.I",
    "team_id": 9956757,
    "team_tag": "LFT",
    "country": "tr"
  },
  {
    "rank": 182,
    "name": "Flokk1n"
  },
  {
    "rank": 183,
    "name": "b4x4zZz",
    "country": "dz"
  },
  {
    "rank": 183,
    "name": "Василий"
  },
  {
    "rank": 185,
    "name": "999",
    "country": "ca"
  },
  {
    "rank": 186,
    "name": "Difference",
    "country": "af"
  },
  {
    "rank": 187,
    "name": "Stormstormer"
  },
  {
    "rank": 188,
    "name": "KG_Zayac",
    "country": "af"
  },
  {
    "rank": 189,
    "name": "Jeezy"
  },
  {
    "rank": 190,
    "name": "Retsu"
  },
  {
    "rank": 191,
    "name": "Dodren",
    "country": "kz"
  },
  {
    "rank": 192,
    "name": "Kai",
    "team_id": 1303618,
    "team_tag": "RH",
    "country": "ua"
  },
  {
    "rank": 193,
    "name": "DarkMago♥"
  },
  {
    "rank": 194,
    "name": "Mira",
    "team_id": 9467224,
    "team_tag": "Aurora",
    "country": "ua"
  },
  {
    "rank": 195,
    "name": "rubikon155"
  },
  {
    "rank": 195,
    "name": "ryota",
    "team_id": 9498970,
    "team_tag": "AVULUS"
  },
  {
    "rank": 197,
    "name": "kreker",
    "team_id": 9928636,
    "team_tag": "LYNX",
    "country": "ua"
  },
  {
    "rank": 198,
    "name": "Krinzhik",
    "country": "pl"
  },
  {
    "rank": 199,
    "name": "Delight"
  },
  {
    "rank": 200,
    "name": "meLes",
    "country": "al"
  },
  {
    "rank": 201,
    "name": "aliez",
    "country": "ru"
  },
  {
    "rank": 202,
    "name": "K4071N"
  },
  {
    "rank": 203,
    "name": "W1sh-",
    "country": "ge"
  },
  {
    "rank": 204,
    "name": "fangyuan"
  },
  {
    "rank": 205,
    "name": "BAKI"
  },
  {
    "rank": 206,
    "name": "Pastil",
    "team_id": 9840188,
    "team_tag": "OXG",
    "country": "dz"
  },
  {
    "rank": 207,
    "name": "budget"
  },
  {
    "rank": 208,
    "name": "Зюзя"
  },
  {
    "rank": 209,
    "name": "ɹǝʞɹɐd⚔️",
    "team_id": 9928403,
    "team_tag": "Cobra",
    "country": "dz"
  },
  {
    "rank": 210,
    "name": "nesfeer",
    "team_id": 55,
    "team_tag": "PR",
    "country": "ax"
  },
  {
    "rank": 211,
    "name": "Mirele`",
    "team_id": 2576071,
    "team_tag": "YeS"
  },
  {
    "rank": 212,
    "name": "天鸽",
    "country": "ca"
  },
  {
    "rank": 213,
    "name": "://"
  },
  {
    "rank": 214,
    "name": "Hero",
    "country": "br"
  },
  {
    "rank": 215,
    "name": "w33",
    "team_id": 10000118,
    "team_tag": "NGX"
  },
  {
    "rank": 216,
    "name": "ряф^^",
    "country": "by"
  },
  {
    "rank": 217,
    "name": "Depk1d",
    "country": "us"
  },
  {
    "rank": 218,
    "name": "Fbz",
    "team_id": 9828897,
    "team_tag": "RKX",
    "country": "id"
  },
  {
    "rank": 219,
    "name": "^^",
    "team_id": 4592013,
    "team_tag": "ааааа",
    "country": "gb"
  },
  {
    "rank": 220,
    "name": "kur0patbI4",
    "country": "by"
  },
  {
    "rank": 221,
    "name": "KoJl9lCuK",
    "country": "dz"
  },
  {
    "rank": 222,
    "name": "Whitemon",
    "team_id": 8291895,
    "team_tag": "Tundra",
    "country": "as"
  },
  {
    "rank": 223,
    "name": "Xakoda",
    "country": "ax"
  },
  {
    "rank": 224,
    "name": "pandaGod",
    "country": "ua"
  },
  {
    "rank": 225,
    "name": "lantana",
    "country": "ua"
  },
  {
    "rank": 226,
    "name": "nefrit",
    "country": "ua"
  },
  {
    "rank": 227,
    "name": "Ulnit"
  },
  {
    "rank": 228,
    "name": "miyaoo",
    "country": "by"
  },
  {
    "rank": 229,
    "name": "Feindaim"
  },
  {
    "rank": 230,
    "name": "gudiny"
  },
  {
    "rank": 231,
    "name": "Moonlight",
    "country": "aw"
  },
  {
    "rank": 232,
    "name": "Cr1t-",
    "team_id": 9247354,
    "team_tag": "FLCN",
    "country": "dk"
  },
  {
    "rank": 233,
    "name": "11",
    "country": "mn"
  },
  {
    "rank": 234,
    "name": "bombi",
    "country": "af"
  },
  {
    "rank": 235,
    "name": "chunga changa"
  },
  {
    "rank": 236,
    "name": "prblms",
    "team_id": 2576071,
    "team_tag": "YeS",
    "country": "ru"
  },
  {
    "rank": 236,
    "name": "NARMAN",
    "country": "mn"
  },
  {
    "rank": 238,
    "name": "xn丶e",
    "country": "ee"
  },
  {
    "rank": 239,
    "name": "kaneki",
    "country": "af"
  },
  {
    "rank": 240,
    "name": "garbat1y"
  },
  {
    "rank": 241,
    "name": "Emrys",
    "country": "ua"
  },
  {
    "rank": 242,
    "name": "Yuma",
    "team_id": 9303484,
    "team_tag": "HEROIC",
    "country": "ni"
  },
  {
    "rank": 243,
    "name": "sdf"
  },
  {
    "rank": 243,
    "name": "adz",
    "country": "gb"
  },
  {
    "rank": 245,
    "name": "xn丶e"
  },
  {
    "rank": 246,
    "name": "Shushu",
    "country": "dz"
  },
  {
    "rank": 246,
    "name": "Son of Shore"
  },
  {
    "rank": 248,
    "name": "Xxs",
    "team_id": 8261500,
    "team_tag": "XG"
  },
  {
    "rank": 248,
    "name": "slimeyao",
    "country": "ru"
  },
  {
    "rank": 250,
    "name": "byun",
    "team_id": 9255225,
    "team_tag": "ease"
  },
  {
    "rank": 251,
    "name": "dota 2 enjoyer =)",
    "country": "al"
  },
  {
    "rank": 252,
    "name": "Egx",
    "country": "by"
  },
  {
    "rank": 253,
    "name": "raze",
    "team_id": 8376426,
    "team_tag": "B8"
  },
  {
    "rank": 254,
    "name": "StoneBank",
    "country": "ua"
  },
  {
    "rank": 255,
    "name": " ",
    "country": "ru"
  },
  {
    "rank": 256,
    "name": "佞臣 ",
    "country": "cn"
  },
  {
    "rank": 257,
    "name": "nochat"
  },
  {
    "rank": 258,
    "name": "Pablo",
    "country": "se"
  },
  {
    "rank": 259,
    "name": "Boxi",
    "team_id": 2163,
    "team_tag": "Liquid",
    "country": "se"
  },
  {
    "rank": 259,
    "name": "Topson",
    "country": "fi"
  },
  {
    "rank": 261,
    "name": "takizawa",
    "team_id": 9872558,
    "team_tag": "VPP",
    "country": "bo"
  },
  {
    "rank": 261,
    "name": "WoE",
    "country": "bo"
  },
  {
    "rank": 263,
    "name": "elmo^^",
    "team_id": 9928623,
    "team_tag": "TNDR.ACDM",
    "country": "kz"
  },
  {
    "rank": 264,
    "name": "tw/styledotaaaa",
    "country": "af"
  },
  {
    "rank": 265,
    "name": "Oshimai",
    "country": "ru"
  },
  {
    "rank": 266,
    "name": "HardL",
    "country": "kz"
  },
  {
    "rank": 267,
    "name": "krol9ash",
    "team_id": 9886393,
    "team_tag": "NAVIj"
  },
  {
    "rank": 268,
    "name": "H8 ",
    "country": "mk"
  },
  {
    "rank": 269,
    "name": "Tox1c",
    "country": "ax"
  },
  {
    "rank": 270,
    "name": "Legend",
    "country": "ua"
  },
  {
    "rank": 271,
    "name": "int'j",
    "country": "af"
  },
  {
    "rank": 272,
    "name": "33",
    "team_id": 8291895,
    "team_tag": "Tundra",
    "country": "il"
  },
  {
    "rank": 273,
    "name": "nattynarwhal_",
    "country": "cr"
  },
  {
    "rank": 274,
    "name": "MTD",
    "team_id": 10054469,
    "team_tag": "X",
    "country": "fi"
  },
  {
    "rank": 275,
    "name": "Covisnine",
    "country": "af"
  },
  {
    "rank": 276,
    "name": "без нытья"
  },
  {
    "rank": 277,
    "name": "QBFY",
    "team_id": 9928636,
    "team_tag": "LYNX",
    "country": "ua"
  },
  {
    "rank": 278,
    "name": "BAKI HANMA ",
    "country": "af"
  },
  {
    "rank": 279,
    "name": "mmr trader"
  },
  {
    "rank": 280,
    "name": "Nikobaby"
  },
  {
    "rank": 281,
    "name": "Simon",
    "country": "gb"
  },
  {
    "rank": 282,
    "name": "Gatciy"
  },
  {
    "rank": 283,
    "name": "Nande"
  },
  {
    "rank": 284,
    "name": "kiyotaka"
  },
  {
    "rank": 285,
    "name": "GodKid (J)",
    "country": "mk"
  },
  {
    "rank": 286,
    "name": "Uch1Ha",
    "country": "ru"
  },
  {
    "rank": 286,
    "name": "Baymax"
  },
  {
    "rank": 288,
    "name": "ᶫᶦᵐᵉʳᵉᶰᶜᵉ̄"
  },
  {
    "rank": 288,
    "name": "selfhate",
    "country": "ru"
  },
  {
    "rank": 290,
    "name": "yaiX",
    "team_id": 9704788,
    "team_tag": "afk",
    "country": "ru"
  },
  {
    "rank": 291,
    "name": "Atouf",
    "country": "fr"
  },
  {
    "rank": 292,
    "name": "333"
  },
  {
    "rank": 293,
    "name": "12"
  },
  {
    "rank": 294,
    "name": "DuBu",
    "team_id": 9997061,
    "team_tag": "PHX",
    "country": "kr"
  },
  {
    "rank": 295,
    "name": "lupsi",
    "country": "ru"
  },
  {
    "rank": 296,
    "name": "rise",
    "team_id": 9744373,
    "team_tag": "LFT",
    "country": "ru"
  },
  {
    "rank": 297,
    "name": "Wuiter",
    "country": "tr"
  },
  {
    "rank": 298,
    "name": "TOMMYQUIONDOTA҈҈҉",
    "country": "mn"
  },
  {
    "rank": 299,
    "name": "9bots"
  },
  {
    "rank": 300,
    "name": "Bignum",
    "team_id": 9964962,
    "team_tag": "GL"
  },
  {
    "rank": 301,
    "name": "m1CKe",
    "team_id": 2163,
    "team_tag": "Liquid",
    "country": "se"
  },
  {
    "rank": 302,
    "name": "pan"
  },
  {
    "rank": 303,
    "name": "PERDAN4IK"
  },
  {
    "rank": 304,
    "name": "unlucky",
    "country": "jp"
  },
  {
    "rank": 305,
    "name": "qoval"
  },
  {
    "rank": 305,
    "name": "1"
  },
  {
    "rank": 307,
    "name": "director導演",
    "country": "ai"
  },
  {
    "rank": 308,
    "name": "tw.tv/clacksontv",
    "country": "ao"
  },
  {
    "rank": 309,
    "name": "hairo~~",
    "team_id": 10000219,
    "team_tag": "Elephant"
  },
  {
    "rank": 310,
    "name": "фикус",
    "team_id": 8562824,
    "team_tag": "Refresh",
    "country": "ph"
  },
  {
    "rank": 311,
    "name": "Seleri"
  },
  {
    "rank": 312,
    "name": "baysk`",
    "country": "mn"
  },
  {
    "rank": 313,
    "name": "hAze._.",
    "country": "kz"
  },
  {
    "rank": 314,
    "name": "ButterflyEffect",
    "country": "tf"
  },
  {
    "rank": 315,
    "name": "white",
    "country": "af"
  },
  {
    "rank": 316,
    "name": "yur",
    "country": "af"
  },
  {
    "rank": 317,
    "name": "йоооуу",
    "team_id": 10048276,
    "team_tag": "EGB"
  },
  {
    "rank": 318,
    "name": "⁧⁧ 󠁳"
  },
  {
    "rank": 319,
    "name": "Jeffrey Epstein"
  },
  {
    "rank": 320,
    "name": "FLee"
  },
  {
    "rank": 321,
    "name": "Hellshock"
  },
  {
    "rank": 322,
    "name": "Ceb",
    "country": "lb"
  },
  {
    "rank": 323,
    "name": "Kaiser~",
    "country": "mn"
  },
  {
    "rank": 324,
    "name": "monodrama",
    "team_id": 9895247,
    "team_tag": "RE",
    "country": "ru"
  },
  {
    "rank": 325,
    "name": "Waneda"
  },
  {
    "rank": 326,
    "name": "zoro",
    "team_id": 9125261,
    "team_tag": "",
    "country": "nz"
  },
  {
    "rank": 327,
    "name": "Zodiac"
  },
  {
    "rank": 328,
    "name": "flacko",
    "country": "ua"
  },
  {
    "rank": 329,
    "name": "Zamir bezgeev",
    "country": "ru"
  },
  {
    "rank": 329,
    "name": "< blank >"
  },
  {
    "rank": 331,
    "name": "Kyoshi",
    "country": "kz"
  },
  {
    "rank": 332,
    "name": "carry/afk",
    "country": "ro"
  },
  {
    "rank": 333,
    "name": "---"
  },
  {
    "rank": 334,
    "name": "Shishak",
    "country": "ru"
  },
  {
    "rank": 335,
    "name": "-een",
    "country": "ax"
  },
  {
    "rank": 336,
    "name": "shiroikiri",
    "country": "ua"
  },
  {
    "rank": 337,
    "name": "Shakh"
  },
  {
    "rank": 338,
    "name": "dalul",
    "team_id": 9828897,
    "team_tag": "RKX",
    "country": "id"
  },
  {
    "rank": 339,
    "name": "L4rks",
    "country": "ee"
  },
  {
    "rank": 340,
    "name": "Wits",
    "country": "pe"
  },
  {
    "rank": 341,
    "name": "Vitaly 誇り",
    "country": "pe"
  },
  {
    "rank": 341,
    "name": "Bat0N"
  },
  {
    "rank": 343,
    "name": "123",
    "country": "mx"
  },
  {
    "rank": 344,
    "name": "pma"
  },
  {
    "rank": 345,
    "name": "LeBronDota"
  },
  {
    "rank": 346,
    "name": "SLATEM$",
    "team_id": 9799043,
    "team_tag": "VB",
    "country": "pe"
  },
  {
    "rank": 347,
    "name": "resonance",
    "country": "ua"
  },
  {
    "rank": 348,
    "name": "Stormy",
    "country": "ge"
  },
  {
    "rank": 349,
    "name": "pacific",
    "country": "ru"
  },
  {
    "rank": 349,
    "name": "piss in the wind",
    "country": "dz"
  },
  {
    "rank": 351,
    "name": "Zoom-ZigZag"
  },
  {
    "rank": 351,
    "name": "Astral",
    "country": "by"
  },
  {
    "rank": 353,
    "name": "Final"
  },
  {
    "rank": 354,
    "name": "...็",
    "country": "by"
  },
  {
    "rank": 355,
    "name": "Kismet",
    "country": "ag"
  },
  {
    "rank": 356,
    "name": "Yopaj-",
    "team_id": 2586976,
    "team_tag": "OG",
    "country": "ph"
  },
  {
    "rank": 357,
    "name": "上头秀丶",
    "country": "ao"
  },
  {
    "rank": 357,
    "name": "имботащер_фемени"
  },
  {
    "rank": 359,
    "name": "Askles^",
    "team_id": 8769827,
    "team_tag": "Erisu",
    "country": "by"
  },
  {
    "rank": 360,
    "name": "король готэма"
  },
  {
    "rank": 360,
    "name": "Nagato LFT"
  },
  {
    "rank": 362,
    "name": "CHAWOT"
  },
  {
    "rank": 363,
    "name": "looking for win"
  },
  {
    "rank": 364,
    "name": "noviy bog",
    "team_id": 9230394,
    "team_tag": "BARCELONA"
  },
  {
    "rank": 365,
    "name": "Шизоид",
    "country": "ru"
  },
  {
    "rank": 366,
    "name": "DaaD-"
  },
  {
    "rank": 367,
    "name": "Katsura",
    "country": "al"
  },
  {
    "rank": 367,
    "name": "BliNcc",
    "team_id": 9948230,
    "team_tag": "twitch.tv",
    "country": "ro"
  },
  {
    "rank": 367,
    "name": "jellyworms.ceo"
  },
  {
    "rank": 370,
    "name": "妓女"
  },
  {
    "rank": 371,
    "name": "Kain",
    "country": "by"
  },
  {
    "rank": 372,
    "name": "xannyy",
    "country": "ru"
  },
  {
    "rank": 373,
    "name": "EndoKardo",
    "country": "ru"
  },
  {
    "rank": 374,
    "name": "ariel",
    "team_id": 10041126,
    "team_tag": "LFT4"
  },
  {
    "rank": 375,
    "name": "erase"
  },
  {
    "rank": 376,
    "name": "Nero",
    "team_id": 8878679,
    "team_tag": "surplus",
    "country": "ru"
  },
  {
    "rank": 376,
    "name": "tv/matsarellow",
    "country": "ua"
  },
  {
    "rank": 378,
    "name": "my tears my loneliness",
    "country": "ru"
  },
  {
    "rank": 379,
    "name": "Szajtek",
    "team_id": 9539470,
    "team_tag": "BOCIAN",
    "country": "pl"
  },
  {
    "rank": 380,
    "name": "Egor",
    "team_id": 9730797,
    "team_tag": "PSK"
  },
  {
    "rank": 381,
    "name": "頑張って",
    "team_id": 9989179,
    "team_tag": "AMG"
  },
  {
    "rank": 381,
    "name": "Grip",
    "team_id": 8376696,
    "team_tag": "Move",
    "country": "ru"
  },
  {
    "rank": 383,
    "name": "arteezysbastark",
    "country": "ga"
  },
  {
    "rank": 384,
    "name": "4nton1das"
  },
  {
    "rank": 385,
    "name": "megoway",
    "country": "eg"
  },
  {
    "rank": 386,
    "name": "prison break"
  },
  {
    "rank": 386,
    "name": "tv/McDodique"
  },
  {
    "rank": 388,
    "name": "ϒāppie"
  },
  {
    "rank": 389,
    "name": "Evernight"
  },
  {
    "rank": 390,
    "name": "Zesky~",
    "team_id": 9840188,
    "team_tag": "OXG"
  },
  {
    "rank": 391,
    "name": "66."
  },
  {
    "rank": 392,
    "name": "=(",
    "team_id": 7612385,
    "team_tag": "",
    "country": "ne"
  },
  {
    "rank": 393,
    "name": "oreomilkshake",
    "country": "ax"
  },
  {
    "rank": 394,
    "name": "Cuziloveyou",
    "team_id": 8496276,
    "team_tag": "BTS",
    "country": "ru"
  },
  {
    "rank": 395,
    "name": "kamaros",
    "country": "ax"
  },
  {
    "rank": 396,
    "name": "qjY"
  },
  {
    "rank": 397,
    "name": "Время в никуда"
  },
  {
    "rank": 398,
    "name": " 86",
    "team_id": 9948367,
    "team_tag": "TSA"
  },
  {
    "rank": 399,
    "name": "mew",
    "country": "ru"
  },
  {
    "rank": 400,
    "name": "alberkaaa",
    "country": "ru"
  },
  {
    "rank": 401,
    "name": "Aui_2000"
  },
  {
    "rank": 402,
    "name": "Mary_y",
    "team_id": 10040974,
    "team_tag": "twitch.tv",
    "country": "kz"
  },
  {
    "rank": 403,
    "name": "tv/depressed11gaga(Gaga)"
  },
  {
    "rank": 404,
    "name": "Lala-troni",
    "team_id": 9081369,
    "team_tag": "Infamous"
  },
  {
    "rank": 405,
    "name": "raregods",
    "team_id": 9872558,
    "team_tag": "VPP",
    "country": "as"
  },
  {
    "rank": 405,
    "name": "Italiano Gangster",
    "country": "us"
  },
  {
    "rank": 407,
    "name": "ryuketsu-",
    "team_id": 9918459,
    "team_tag": "lowskill",
    "country": "at"
  },
  {
    "rank": 408,
    "name": "Айхан"
  },
  {
    "rank": 408,
    "name": "Senku"
  },
  {
    "rank": 410,
    "name": "паук"
  },
  {
    "rank": 411,
    "name": "Matthew"
  },
  {
    "rank": 412,
    "name": "MugzZ",
    "team_id": 9381006,
    "team_tag": "LFT5",
    "country": "ru"
  },
  {
    "rank": 413,
    "name": "-DragonSouL"
  },
  {
    "rank": 414,
    "name": "Genek"
  },
  {
    "rank": 415,
    "name": "MYNIGGAZWEDONTDANCEWEJUSTPULLUOU",
    "country": "af"
  },
  {
    "rank": 416,
    "name": "Belony`",
    "country": "ua"
  },
  {
    "rank": 416,
    "name": "tv/sketcher",
    "country": "ua"
  },
  {
    "rank": 418,
    "name": "Re{Ali}Ty"
  },
  {
    "rank": 419,
    "name": "monke",
    "country": "ru"
  },
  {
    "rank": 420,
    "name": "puckish229"
  },
  {
    "rank": 421,
    "name": "Kurisutina~",
    "country": "mn"
  },
  {
    "rank": 422,
    "name": "RHLM",
    "country": "pe"
  },
  {
    "rank": 423,
    "name": "kiska"
  },
  {
    "rank": 424,
    "name": "Krish",
    "team_id": 9989175,
    "team_tag": "LFT",
    "country": "in"
  },
  {
    "rank": 425,
    "name": "case",
    "country": "ad"
  },
  {
    "rank": 426,
    "name": "Moku"
  },
  {
    "rank": 427,
    "name": "Nizam`",
    "country": "az"
  },
  {
    "rank": 428,
    "name": "Starlight-",
    "country": "ag"
  },
  {
    "rank": 429,
    "name": "pop"
  },
  {
    "rank": 430,
    "name": "eva",
    "country": "ec"
  },
  {
    "rank": 430,
    "name": "Yadomichi"
  },
  {
    "rank": 432,
    "name": "G6"
  },
  {
    "rank": 433,
    "name": "egn",
    "country": "by"
  },
  {
    "rank": 434,
    "name": "hwoarang",
    "country": "af"
  },
  {
    "rank": 435,
    "name": "layme"
  },
  {
    "rank": 435,
    "name": "Elmisho",
    "team_id": 9928403,
    "team_tag": "Cobra",
    "country": "pe"
  },
  {
    "rank": 437,
    "name": "Depressed"
  },
  {
    "rank": 438,
    "name": "天堂"
  },
  {
    "rank": 438,
    "name": "Cooman",
    "country": "ru"
  },
  {
    "rank": 440,
    "name": "Sneaky",
    "country": "tr"
  },
  {
    "rank": 441,
    "name": "beautiful world",
    "country": "ru"
  },
  {
    "rank": 442,
    "name": "Ronaldo"
  },
  {
    "rank": 443,
    "name": "eblan",
    "team_id": 8359893,
    "team_tag": ""
  },
  {
    "rank": 444,
    "name": "Q7",
    "team_id": 9886289,
    "team_tag": "",
    "country": "ag"
  },
  {
    "rank": 445,
    "name": "Michael~",
    "team_id": 9989179,
    "team_tag": "AMG",
    "country": "bo"
  },
  {
    "rank": 446,
    "name": "< blank >"
  },
  {
    "rank": 447,
    "name": "91",
    "country": "sg"
  },
  {
    "rank": 447,
    "name": "Akamu",
    "team_id": 9571742,
    "team_tag": "",
    "country": "ua"
  },
  {
    "rank": 449,
    "name": "Ax.Mo"
  },
  {
    "rank": 450,
    "name": "type london"
  },
  {
    "rank": 451,
    "name": "Escape from reality"
  },
  {
    "rank": 452,
    "name": "none",
    "country": "ru"
  },
  {
    "rank": 453,
    "name": ")"
  },
  {
    "rank": 454,
    "name": "Attacker",
    "country": "ae"
  },
  {
    "rank": 455,
    "name": "Gabriel"
  },
  {
    "rank": 456,
    "name": "VΔ4",
    "country": "ru"
  },
  {
    "rank": 457,
    "name": "UndeRRwhatt"
  },
  {
    "rank": 457,
    "name": "Asfreed"
  },
  {
    "rank": 459,
    "name": "fam0us",
    "country": "ru"
  },
  {
    "rank": 460,
    "name": "Fishman",
    "country": "by"
  },
  {
    "rank": 461,
    "name": "highroller"
  },
  {
    "rank": 462,
    "name": "克服"
  },
  {
    "rank": 463,
    "name": "Purpurbl4"
  },
  {
    "rank": 464,
    "name": "Bóbr",
    "country": "ug"
  },
  {
    "rank": 465,
    "name": "zahn",
    "country": "ax"
  },
  {
    "rank": 466,
    "name": "Muf",
    "country": "cz"
  },
  {
    "rank": 467,
    "name": "ShamPure",
    "country": "ru"
  },
  {
    "rank": 468,
    "name": "reibl"
  },
  {
    "rank": 469,
    "name": "красавчик",
    "country": "ca"
  },
  {
    "rank": 470,
    "name": "fcr",
    "team_id": 9499095,
    "team_tag": "LGCY",
    "country": "br"
  },
  {
    "rank": 471,
    "name": "tv/maloydotos",
    "team_id": 9374340,
    "team_tag": "twitch"
  },
  {
    "rank": 472,
    "name": "klseki",
    "team_id": 8562032,
    "team_tag": "",
    "country": "ua"
  },
  {
    "rank": 473,
    "name": "KnowLedgE-",
    "team_id": 8589454,
    "team_tag": "FP",
    "country": "af"
  },
  {
    "rank": 474,
    "name": "abube",
    "team_id": 9628573,
    "team_tag": ""
  },
  {
    "rank": 475,
    "name": "matshah",
    "country": "ua"
  },
  {
    "rank": 476,
    "name": "ᐸ/3"
  },
  {
    "rank": 477,
    "name": "Cold-",
    "country": "af"
  },
  {
    "rank": 478,
    "name": "xsvampire ",
    "team_id": 10047709,
    "team_tag": "ILBIRS",
    "country": "kz"
  },
  {
    "rank": 479,
    "name": "根性 Nanami",
    "country": "ua"
  },
  {
    "rank": 480,
    "name": "the soloist"
  },
  {
    "rank": 481,
    "name": "tv/johnnupro",
    "country": "ua"
  },
  {
    "rank": 482,
    "name": "ComicS"
  },
  {
    "rank": 483,
    "name": "神龙大侠 - 最强熊猫",
    "country": "jp"
  },
  {
    "rank": 484,
    "name": "約束",
    "country": "pe"
  },
  {
    "rank": 485,
    "name": "tv/fsdjke",
    "country": "ru"
  },
  {
    "rank": 486,
    "name": "Tamybaby",
    "country": "mn"
  },
  {
    "rank": 487,
    "name": "Abomination"
  },
  {
    "rank": 488,
    "name": "aNewMe",
    "team_id": 9292644,
    "team_tag": ""
  },
  {
    "rank": 489,
    "name": "Surrender",
    "country": "va"
  },
  {
    "rank": 490,
    "name": "Max"
  },
  {
    "rank": 491,
    "name": "dota player"
  },
  {
    "rank": 492,
    "name": "Sacred"
  },
  {
    "rank": 493,
    "name": "baka",
    "country": "bm"
  },
  {
    "rank": 494,
    "name": "tv/iloveokaydoto",
    "country": "af"
  },
  {
    "rank": 495,
    "name": "ancleve`",
    "country": "ru"
  },
  {
    "rank": 496,
    "name": "333"
  },
  {
    "rank": 497,
    "name": "Monhty"
  },
  {
    "rank": 498,
    "name": "krylat",
    "country": "ru"
  },
  {
    "rank": 499,
    "name": "SPLINTER"
  },
  {
    "rank": 499,
    "name": "AtoMic"
  }
]
